bgremv/__init__.py
bgremv/main.py
bgremv_aditx-0.2.0.dist-info/METADATA
bgremv_aditx-0.2.0.dist-info/WHEEL
bgremv_aditx-0.2.0.dist-info/top_level.txt
bgremv_aditx-0.2.0.dist-info/RECORD
