Metadata-Version: 2.4
Name: bgremv-aditx
Version: 0.2.0
Summary: A simple package to remove image backgrounds using rembg.
Author: Aditya
Author-email: aditxgupta@gmail.com
Classifier: Programming Language :: Python :: 3
Classifier: License :: OSI Approved :: MIT License
Classifier: Operating System :: OS Independent
Requires-Python: >=3.7
Dynamic: author
Dynamic: author-email
Dynamic: classifier
Dynamic: requires-python
Dynamic: summary
